{
  "version": "1.0",
  "created": "2026-05-18T00:55:17.344Z",
  "reset_reason": "Mon 5/18 pre-RTH reset after Sun 5/17 20:04-20:06 ET catastrophic failure (-$19,173 cascade). Operator chose $10K starting balance.",
  "mode": "PAPER",
  "instruments": [
    "ES1!",
    "NQ1!",
    "MES1!",
    "MNQ1!"
  ],
  "balance": 9838.75,
  "startBalance": 10000,
  "totalPnL": -161.25,
  "totalTrades": 20,
  "wins": 7,
  "losses": 13,
  "trades": [
    {
      "requestId": "FUT_CALLS_HL_1779071039640_1",
      "instrument": "MES1!",
      "signal": "CALLS",
      "engine": "HL",
      "confidence": "MEDIUM",
      "tier": "B",
      "contracts": 1,
      "originalContracts": 1,
      "entryPrice": 7390.75,
      "fillPrice": 7390.75,
      "fillTime": 1779071039658,
      "fillTimeET": "22:23:59",
      "entryTimeET": "22:23:59",
      "pointValue": 5,
      "stage": "STAGE_1_ARMED",
      "stopPrice": 7387.75,
      "stopPoints": 3,
      "targetPrice": 7395.75,
      "targetPoints": 5,
      "peakFavorablePrice": 7390.75,
      "trailStopPrice": null,
      "lockedStopLevel": "NONE",
      "cumulativePartialPnL": 0,
      "scaleOutEvents": [],
      "macro4H": "UNKNOWN",
      "invalidationLevel": null,
      "structureType": null,
      "status": "CLOSED",
      "exitPrice": 7385.75,
      "exitTime": 1779073260262,
      "pnl": -25,
      "paper": true,
      "mode": "PAPER",
      "exitTimeET": "23:01:00",
      "exitReason": "FUT_STOP_HIT",
      "pnlPoints": -5,
      "pnlRemainingLeg": -25,
      "holdMins": 37,
      "win": false
    },
    {
      "requestId": "FUT_PUTS_LH_1779071339387_6",
      "instrument": "MES1!",
      "signal": "PUTS",
      "engine": "LH",
      "confidence": "MEDIUM",
      "tier": "B",
      "contracts": 0,
      "originalContracts": 1,
      "entryPrice": 7391.5,
      "fillPrice": 7391.5,
      "fillTime": 1779071339406,
      "fillTimeET": "22:28:59",
      "entryTimeET": "22:28:59",
      "pointValue": 5,
      "stage": "STAGE_3_TRAILING",
      "stopPrice": 7382.214,
      "stopPoints": 3,
      "targetPrice": 7386.5,
      "targetPoints": 5,
      "peakFavorablePrice": 7380,
      "trailStopPrice": 7382.214,
      "lockedStopLevel": "1R",
      "cumulativePartialPnL": 26.25,
      "scaleOutEvents": [
        {
          "contracts": 1,
          "exitPrice": 7386.25,
          "exitTime": 1779072480583,
          "et": "22:48:00",
          "pnl": 26.25,
          "reason": "FUT_SCALE_OUT_PARTIAL",
          "underlyingAtExit": 7386.25
        }
      ],
      "macro4H": "UNKNOWN",
      "invalidationLevel": null,
      "structureType": null,
      "status": "CLOSED",
      "exitPrice": 7382.75,
      "exitTime": 1779075300544,
      "pnl": 26.25,
      "paper": true,
      "mode": "PAPER",
      "exitTimeET": "23:35:00",
      "exitReason": "FUT_PROFIT_LOCKED_STOP",
      "pnlPoints": 8.75,
      "pnlRemainingLeg": 0,
      "holdMins": 66,
      "win": true
    },
    {
      "requestId": "FUT_CALLS_HL_1779071519897_7",
      "instrument": "MES1!",
      "signal": "CALLS",
      "engine": "HL",
      "confidence": "MEDIUM",
      "tier": "B",
      "contracts": 1,
      "originalContracts": 1,
      "entryPrice": 7391.5,
      "fillPrice": 7391.5,
      "fillTime": 1779071519915,
      "fillTimeET": "22:31:59",
      "entryTimeET": "22:31:59",
      "pointValue": 5,
      "stage": "STAGE_1_ARMED",
      "stopPrice": 7388.5,
      "stopPoints": 3,
      "targetPrice": 7396.5,
      "targetPoints": 5,
      "peakFavorablePrice": 7391.5,
      "trailStopPrice": null,
      "lockedStopLevel": "NONE",
      "cumulativePartialPnL": 0,
      "scaleOutEvents": [],
      "macro4H": "UNKNOWN",
      "invalidationLevel": null,
      "structureType": null,
      "status": "CLOSED",
      "exitPrice": 7385.75,
      "exitTime": 1779073260266,
      "pnl": -28.75,
      "paper": true,
      "mode": "PAPER",
      "exitTimeET": "23:01:00",
      "exitReason": "FUT_STOP_HIT",
      "pnlPoints": -5.75,
      "pnlRemainingLeg": -28.75,
      "holdMins": 29,
      "win": false
    },
    {
      "requestId": "FUT_PUTS_ZONE_1779071580053_a",
      "instrument": "MES1!",
      "signal": "PUTS",
      "engine": "ZONE",
      "confidence": "MEDIUM",
      "tier": "B",
      "contracts": 0,
      "originalContracts": 1,
      "entryPrice": 7389.75,
      "fillPrice": 7389.75,
      "fillTime": 1779071580070,
      "fillTimeET": "22:33:00",
      "entryTimeET": "22:33:00",
      "pointValue": 5,
      "stage": "STAGE_3_TRAILING",
      "stopPrice": 7382.214,
      "stopPoints": 3,
      "targetPrice": 7384.75,
      "targetPoints": 5,
      "peakFavorablePrice": 7380,
      "trailStopPrice": 7382.214,
      "lockedStopLevel": "1R",
      "cumulativePartialPnL": 30,
      "scaleOutEvents": [
        {
          "contracts": 1,
          "exitPrice": 7383.75,
          "exitTime": 1779074160746,
          "et": "23:16:00",
          "pnl": 30,
          "reason": "FUT_SCALE_OUT_PARTIAL",
          "underlyingAtExit": 7383.75
        }
      ],
      "macro4H": "UNKNOWN",
      "invalidationLevel": null,
      "structureType": null,
      "status": "CLOSED",
      "exitPrice": 7382.75,
      "exitTime": 1779075300548,
      "pnl": 30,
      "paper": true,
      "mode": "PAPER",
      "exitTimeET": "23:35:00",
      "exitReason": "FUT_PROFIT_LOCKED_STOP",
      "pnlPoints": 7,
      "pnlRemainingLeg": 0,
      "holdMins": 62,
      "win": true
    },
    {
      "requestId": "FUT_PUTS_ZONE_1779071700327_b",
      "instrument": "MES1!",
      "signal": "PUTS",
      "engine": "ZONE",
      "confidence": "MEDIUM",
      "tier": "B",
      "contracts": 0,
      "originalContracts": 1,
      "entryPrice": 7389.25,
      "fillPrice": 7389.25,
      "fillTime": 1779071700342,
      "fillTimeET": "22:35:00",
      "entryTimeET": "22:35:00",
      "pointValue": 5,
      "stage": "STAGE_3_TRAILING",
      "stopPrice": 7382.214,
      "stopPoints": 3,
      "targetPrice": 7384.25,
      "targetPoints": 5,
      "peakFavorablePrice": 7380,
      "trailStopPrice": 7382.214,
      "lockedStopLevel": "1R",
      "cumulativePartialPnL": 27.5,
      "scaleOutEvents": [
        {
          "contracts": 1,
          "exitPrice": 7383.75,
          "exitTime": 1779074160749,
          "et": "23:16:00",
          "pnl": 27.5,
          "reason": "FUT_SCALE_OUT_PARTIAL",
          "underlyingAtExit": 7383.75
        }
      ],
      "macro4H": "UNKNOWN",
      "invalidationLevel": null,
      "structureType": null,
      "status": "CLOSED",
      "exitPrice": 7382.75,
      "exitTime": 1779075300551,
      "pnl": 27.5,
      "paper": true,
      "mode": "PAPER",
      "exitTimeET": "23:35:00",
      "exitReason": "FUT_PROFIT_LOCKED_STOP",
      "pnlPoints": 6.5,
      "pnlRemainingLeg": 0,
      "holdMins": 60,
      "win": true
    },
    {
      "requestId": "FUT_PUTS_LH_1779072479428_l",
      "instrument": "MES1!",
      "signal": "PUTS",
      "engine": "LH",
      "confidence": "MEDIUM",
      "tier": "B",
      "contracts": 0,
      "originalContracts": 1,
      "entryPrice": 7386.25,
      "fillPrice": 7386.25,
      "fillTime": 1779072479445,
      "fillTimeET": "22:47:59",
      "entryTimeET": "22:47:59",
      "pointValue": 5,
      "stage": "STAGE_3_TRAILING",
      "stopPrice": 7382.214,
      "stopPoints": 3,
      "targetPrice": 7381.25,
      "targetPoints": 5,
      "peakFavorablePrice": 7380,
      "trailStopPrice": 7382.214,
      "lockedStopLevel": "NONE",
      "cumulativePartialPnL": 31.25,
      "scaleOutEvents": [
        {
          "contracts": 1,
          "exitPrice": 7380,
          "exitTime": 1779075044422,
          "et": "23:30:44",
          "pnl": 31.25,
          "reason": "FUT_SCALE_OUT_PARTIAL",
          "underlyingAtExit": 7380
        }
      ],
      "macro4H": "UNKNOWN",
      "invalidationLevel": null,
      "structureType": null,
      "status": "CLOSED",
      "exitPrice": 7385.25,
      "exitTime": 1779075660607,
      "pnl": 31.25,
      "paper": true,
      "mode": "PAPER",
      "exitTimeET": "23:41:00",
      "exitReason": "FUT_STOP_HIT",
      "pnlPoints": 1,
      "pnlRemainingLeg": 0,
      "holdMins": 53,
      "win": true
    },
    {
      "requestId": "FUT_PUTS_HTF_1779072479464_m",
      "instrument": "MES1!",
      "signal": "PUTS",
      "engine": "HTF",
      "confidence": "HIGH",
      "tier": "A",
      "contracts": 0,
      "originalContracts": 1,
      "entryPrice": 7386.25,
      "fillPrice": 7386.25,
      "fillTime": 1779072479482,
      "fillTimeET": "22:47:59",
      "entryTimeET": "22:47:59",
      "pointValue": 5,
      "stage": "STAGE_3_TRAILING",
      "stopPrice": 7382.214,
      "stopPoints": 3,
      "targetPrice": 7380.25,
      "targetPoints": 6,
      "peakFavorablePrice": 7380,
      "trailStopPrice": 7382.214,
      "lockedStopLevel": "NONE",
      "cumulativePartialPnL": 31.25,
      "scaleOutEvents": [
        {
          "contracts": 1,
          "exitPrice": 7380,
          "exitTime": 1779075044425,
          "et": "23:30:44",
          "pnl": 31.25,
          "reason": "FUT_SCALE_OUT_PARTIAL",
          "underlyingAtExit": 7380
        }
      ],
      "macro4H": "UNKNOWN",
      "invalidationLevel": null,
      "structureType": null,
      "status": "CLOSED",
      "exitPrice": 7385.25,
      "exitTime": 1779075660610,
      "pnl": 31.25,
      "paper": true,
      "mode": "PAPER",
      "exitTimeET": "23:41:00",
      "exitReason": "FUT_STOP_HIT",
      "pnlPoints": 1,
      "pnlRemainingLeg": 0,
      "holdMins": 53,
      "win": true
    },
    {
      "requestId": "FUT_PUTS_SELL_1779072479503_n",
      "instrument": "MES1!",
      "signal": "PUTS",
      "engine": "SELL",
      "confidence": "MEDIUM",
      "tier": "A",
      "contracts": 0,
      "originalContracts": 1,
      "entryPrice": 7386.25,
      "fillPrice": 7386.25,
      "fillTime": 1779072479520,
      "fillTimeET": "22:47:59",
      "entryTimeET": "22:47:59",
      "pointValue": 5,
      "stage": "STAGE_3_TRAILING",
      "stopPrice": 7382.214,
      "stopPoints": 3,
      "targetPrice": 7380.25,
      "targetPoints": 6,
      "peakFavorablePrice": 7380,
      "trailStopPrice": 7382.214,
      "lockedStopLevel": "NONE",
      "cumulativePartialPnL": 31.25,
      "scaleOutEvents": [
        {
          "contracts": 1,
          "exitPrice": 7380,
          "exitTime": 1779075044427,
          "et": "23:30:44",
          "pnl": 31.25,
          "reason": "FUT_SCALE_OUT_PARTIAL",
          "underlyingAtExit": 7380
        }
      ],
      "macro4H": "UNKNOWN",
      "invalidationLevel": null,
      "structureType": null,
      "status": "CLOSED",
      "exitPrice": 7385.25,
      "exitTime": 1779075660613,
      "pnl": 31.25,
      "paper": true,
      "mode": "PAPER",
      "exitTimeET": "23:41:00",
      "exitReason": "FUT_STOP_HIT",
      "pnlPoints": 1,
      "pnlRemainingLeg": 0,
      "holdMins": 53,
      "win": true
    },
    {
      "requestId": "FUT_CALLS_ZONE_1779073260071_o",
      "instrument": "MES1!",
      "signal": "CALLS",
      "engine": "ZONE",
      "confidence": "MEDIUM",
      "tier": "B",
      "contracts": 1,
      "originalContracts": 1,
      "entryPrice": 7385.75,
      "fillPrice": 7385.75,
      "fillTime": 1779073260090,
      "fillTimeET": "23:01:00",
      "entryTimeET": "23:01:00",
      "pointValue": 5,
      "stage": "STAGE_1_ARMED",
      "stopPrice": 7382.75,
      "stopPoints": 3,
      "targetPrice": 7390.75,
      "targetPoints": 5,
      "peakFavorablePrice": 7385.75,
      "trailStopPrice": null,
      "lockedStopLevel": "NONE",
      "cumulativePartialPnL": 0,
      "scaleOutEvents": [],
      "macro4H": "UNKNOWN",
      "invalidationLevel": null,
      "structureType": null,
      "status": "CLOSED",
      "exitPrice": 7381,
      "exitTime": 1779075061009,
      "pnl": -23.75,
      "paper": true,
      "mode": "PAPER",
      "exitTimeET": "23:31:01",
      "exitReason": "FUT_STOP_HIT",
      "pnlPoints": -4.75,
      "pnlRemainingLeg": -23.75,
      "holdMins": 30,
      "win": false
    },
    {
      "requestId": "FUT_CALLS_BUY_1779073261415_r",
      "instrument": "MES1!",
      "signal": "CALLS",
      "engine": "BUY",
      "confidence": "MEDIUM",
      "tier": "A",
      "contracts": 1,
      "originalContracts": 1,
      "entryPrice": 7385.75,
      "fillPrice": 7385.75,
      "fillTime": 1779073261431,
      "fillTimeET": "23:01:01",
      "entryTimeET": "23:01:01",
      "pointValue": 5,
      "stage": "STAGE_1_ARMED",
      "stopPrice": 7382.75,
      "stopPoints": 3,
      "targetPrice": 7391.75,
      "targetPoints": 6,
      "peakFavorablePrice": 7385.75,
      "trailStopPrice": null,
      "lockedStopLevel": "NONE",
      "cumulativePartialPnL": 0,
      "scaleOutEvents": [],
      "macro4H": "UNKNOWN",
      "invalidationLevel": null,
      "structureType": null,
      "status": "CLOSED",
      "exitPrice": 7381,
      "exitTime": 1779075061012,
      "pnl": -23.75,
      "paper": true,
      "mode": "PAPER",
      "exitTimeET": "23:31:01",
      "exitReason": "FUT_STOP_HIT",
      "pnlPoints": -4.75,
      "pnlRemainingLeg": -23.75,
      "holdMins": 30,
      "win": false
    },
    {
      "requestId": "FUT_PUTS_ZONE_1779111899469_0",
      "instrument": "MES1!",
      "signal": "PUTS",
      "engine": "ZONE",
      "confidence": "MEDIUM",
      "tier": "B",
      "contracts": 1,
      "originalContracts": 1,
      "entryPrice": 7420,
      "fillPrice": 7420,
      "fillTime": 1779111899489,
      "fillTimeET": "09:44:59",
      "entryTimeET": "09:44:59",
      "pointValue": 5,
      "stage": "STAGE_1_ARMED",
      "stopPrice": 7423,
      "stopPoints": 3,
      "targetPrice": 7415,
      "targetPoints": 5,
      "peakFavorablePrice": 7420,
      "trailStopPrice": null,
      "lockedStopLevel": "NONE",
      "cumulativePartialPnL": 0,
      "scaleOutEvents": [],
      "macro4H": "RANGING",
      "invalidationLevel": null,
      "structureType": null,
      "status": "CLOSED",
      "exitPrice": 7424.25,
      "exitTime": 1779111961172,
      "pnl": -21.25,
      "paper": true,
      "mode": "PAPER",
      "exitTimeET": "09:46:01",
      "exitReason": "FUT_STOP_HIT",
      "pnlPoints": -4.25,
      "pnlRemainingLeg": -21.25,
      "holdMins": 1,
      "win": false
    },
    {
      "requestId": "FUT_PUTS_SELL_1779112019170_4",
      "instrument": "MES1!",
      "signal": "PUTS",
      "engine": "SELL",
      "confidence": "MEDIUM",
      "tier": "B",
      "contracts": 1,
      "originalContracts": 1,
      "entryPrice": 7422.25,
      "fillPrice": 7422.25,
      "fillTime": 1779112019187,
      "fillTimeET": "09:46:59",
      "entryTimeET": "09:46:59",
      "pointValue": 5,
      "stage": "STAGE_1_ARMED",
      "stopPrice": 7425.25,
      "stopPoints": 3,
      "targetPrice": 7417.25,
      "targetPoints": 5,
      "peakFavorablePrice": 7422.25,
      "trailStopPrice": null,
      "lockedStopLevel": "NONE",
      "cumulativePartialPnL": 0,
      "scaleOutEvents": [],
      "macro4H": "RANGING",
      "invalidationLevel": null,
      "structureType": null,
      "status": "CLOSED",
      "exitPrice": 7429.75,
      "exitTime": 1779112080251,
      "pnl": -37.5,
      "paper": true,
      "mode": "PAPER",
      "exitTimeET": "09:48:00",
      "exitReason": "FUT_STOP_HIT",
      "pnlPoints": -7.5,
      "pnlRemainingLeg": -37.5,
      "holdMins": 1,
      "win": false
    },
    {
      "requestId": "FUT_PUTS_HTF_1779112019271_5",
      "instrument": "MES1!",
      "signal": "PUTS",
      "engine": "HTF",
      "confidence": "HIGH",
      "tier": "A",
      "contracts": 1,
      "originalContracts": 1,
      "entryPrice": 7422.25,
      "fillPrice": 7422.25,
      "fillTime": 1779112019288,
      "fillTimeET": "09:46:59",
      "entryTimeET": "09:46:59",
      "pointValue": 5,
      "stage": "STAGE_1_ARMED",
      "stopPrice": 7425.25,
      "stopPoints": 3,
      "targetPrice": 7416.25,
      "targetPoints": 6,
      "peakFavorablePrice": 7422.25,
      "trailStopPrice": null,
      "lockedStopLevel": "NONE",
      "cumulativePartialPnL": 0,
      "scaleOutEvents": [],
      "macro4H": "RANGING",
      "invalidationLevel": null,
      "structureType": null,
      "status": "CLOSED",
      "exitPrice": 7429.75,
      "exitTime": 1779112080254,
      "pnl": -37.5,
      "paper": true,
      "mode": "PAPER",
      "exitTimeET": "09:48:00",
      "exitReason": "FUT_STOP_HIT",
      "pnlPoints": -7.5,
      "pnlRemainingLeg": -37.5,
      "holdMins": 1,
      "win": false
    },
    {
      "requestId": "FUT_PUTS_LH_1779112019311_6",
      "instrument": "MES1!",
      "signal": "PUTS",
      "engine": "LH",
      "confidence": "MEDIUM",
      "tier": "A",
      "contracts": 1,
      "originalContracts": 1,
      "entryPrice": 7422.25,
      "fillPrice": 7422.25,
      "fillTime": 1779112019330,
      "fillTimeET": "09:46:59",
      "entryTimeET": "09:46:59",
      "pointValue": 5,
      "stage": "STAGE_1_ARMED",
      "stopPrice": 7425.25,
      "stopPoints": 3,
      "targetPrice": 7416.25,
      "targetPoints": 6,
      "peakFavorablePrice": 7422.25,
      "trailStopPrice": null,
      "lockedStopLevel": "NONE",
      "cumulativePartialPnL": 0,
      "scaleOutEvents": [],
      "macro4H": "RANGING",
      "invalidationLevel": null,
      "structureType": null,
      "status": "CLOSED",
      "exitPrice": 7429.75,
      "exitTime": 1779112080259,
      "pnl": -37.5,
      "paper": true,
      "mode": "PAPER",
      "exitTimeET": "09:48:00",
      "exitReason": "FUT_STOP_HIT",
      "pnlPoints": -7.5,
      "pnlRemainingLeg": -37.5,
      "holdMins": 1,
      "win": false
    },
    {
      "requestId": "FUT_PUTS_LH_1779114599078_m",
      "instrument": "MES1!",
      "signal": "PUTS",
      "engine": "LH",
      "confidence": "MEDIUM",
      "tier": "B",
      "contracts": 1,
      "originalContracts": 1,
      "entryPrice": 7435.25,
      "fillPrice": 7435.25,
      "fillTime": 1779114599097,
      "fillTimeET": "10:29:59",
      "entryTimeET": "10:29:59",
      "pointValue": 5,
      "stage": "STAGE_1_ARMED",
      "stopPrice": 7438.25,
      "stopPoints": 3,
      "targetPrice": 7430.25,
      "targetPoints": 5,
      "peakFavorablePrice": 7435.25,
      "trailStopPrice": null,
      "lockedStopLevel": "NONE",
      "cumulativePartialPnL": 0,
      "scaleOutEvents": [],
      "macro4H": "RANGING",
      "invalidationLevel": null,
      "structureType": null,
      "status": "CLOSED",
      "exitPrice": 7418.75,
      "exitTime": 1779115299483,
      "pnl": 82.5,
      "paper": true,
      "mode": "PAPER",
      "exitTimeET": "10:41:39",
      "exitReason": "OPERATOR_FORCE_CLOSE",
      "pnlPoints": 16.5,
      "pnlRemainingLeg": 82.5,
      "holdMins": 11.7,
      "win": true
    },
    {
      "requestId": "FUT_PUTS_HTF_1779115679345_3",
      "instrument": "MES1!",
      "signal": "PUTS",
      "engine": "HTF",
      "confidence": "HIGH",
      "tier": "A",
      "contracts": 1,
      "originalContracts": 1,
      "entryPrice": 7418,
      "fillPrice": 7418,
      "fillTime": 1779115679365,
      "fillTimeET": "10:47:59",
      "entryTimeET": "10:47:59",
      "pointValue": 5,
      "stage": "STAGE_1_ARMED",
      "stopPrice": 7421,
      "stopPoints": 3,
      "targetPrice": 7412,
      "targetPoints": 6,
      "peakFavorablePrice": 7418,
      "trailStopPrice": null,
      "lockedStopLevel": "NONE",
      "cumulativePartialPnL": 0,
      "scaleOutEvents": [],
      "macro4H": "RANGING",
      "invalidationLevel": null,
      "structureType": null,
      "status": "CLOSED",
      "exitPrice": 7425.75,
      "exitTime": 1779115980692,
      "pnl": -38.75,
      "paper": true,
      "mode": "PAPER",
      "exitTimeET": "10:53:00",
      "exitReason": "FUT_STOP_HIT",
      "pnlPoints": -7.75,
      "pnlRemainingLeg": -38.75,
      "holdMins": 5,
      "win": false
    },
    {
      "requestId": "FUT_PUTS_LH_1779115679389_4",
      "instrument": "MES1!",
      "signal": "PUTS",
      "engine": "LH",
      "confidence": "MEDIUM",
      "tier": "A",
      "contracts": 1,
      "originalContracts": 1,
      "entryPrice": 7418,
      "fillPrice": 7418,
      "fillTime": 1779115679409,
      "fillTimeET": "10:47:59",
      "entryTimeET": "10:47:59",
      "pointValue": 5,
      "stage": "STAGE_1_ARMED",
      "stopPrice": 7421,
      "stopPoints": 3,
      "targetPrice": 7412,
      "targetPoints": 6,
      "peakFavorablePrice": 7418,
      "trailStopPrice": null,
      "lockedStopLevel": "NONE",
      "cumulativePartialPnL": 0,
      "scaleOutEvents": [],
      "macro4H": "RANGING",
      "invalidationLevel": null,
      "structureType": null,
      "status": "CLOSED",
      "exitPrice": 7425.75,
      "exitTime": 1779115980699,
      "pnl": -38.75,
      "paper": true,
      "mode": "PAPER",
      "exitTimeET": "10:53:00",
      "exitReason": "FUT_STOP_HIT",
      "pnlPoints": -7.75,
      "pnlRemainingLeg": -38.75,
      "holdMins": 5,
      "win": false
    },
    {
      "requestId": "FUT_PUTS_SELL_1779115680393_8",
      "instrument": "MES1!",
      "signal": "PUTS",
      "engine": "SELL",
      "confidence": "MEDIUM",
      "tier": "A",
      "contracts": 1,
      "originalContracts": 1,
      "entryPrice": 7418,
      "fillPrice": 7418,
      "fillTime": 1779115680412,
      "fillTimeET": "10:48:00",
      "entryTimeET": "10:48:00",
      "pointValue": 5,
      "stage": "STAGE_1_ARMED",
      "stopPrice": 7421,
      "stopPoints": 3,
      "targetPrice": 7412,
      "targetPoints": 6,
      "peakFavorablePrice": 7418,
      "trailStopPrice": null,
      "lockedStopLevel": "NONE",
      "cumulativePartialPnL": 0,
      "scaleOutEvents": [],
      "macro4H": "RANGING",
      "invalidationLevel": null,
      "structureType": null,
      "status": "CLOSED",
      "exitPrice": 7425.75,
      "exitTime": 1779115980709,
      "pnl": -38.75,
      "paper": true,
      "mode": "PAPER",
      "exitTimeET": "10:53:00",
      "exitReason": "FUT_STOP_HIT",
      "pnlPoints": -7.75,
      "pnlRemainingLeg": -38.75,
      "holdMins": 5,
      "win": false
    },
    {
      "requestId": "FUT_CALLS_BUY_1779115979078_b",
      "instrument": "MES1!",
      "signal": "CALLS",
      "engine": "BUY",
      "confidence": "MEDIUM",
      "tier": "B",
      "contracts": 1,
      "originalContracts": 1,
      "entryPrice": 7425.75,
      "fillPrice": 7425.75,
      "fillTime": 1779115979126,
      "fillTimeET": "10:52:59",
      "entryTimeET": "10:52:59",
      "pointValue": 5,
      "stage": "STAGE_1_ARMED",
      "stopPrice": 7422.75,
      "stopPoints": 3,
      "targetPrice": 7430.75,
      "targetPoints": 5,
      "peakFavorablePrice": 7425.75,
      "trailStopPrice": null,
      "lockedStopLevel": "NONE",
      "cumulativePartialPnL": 0,
      "scaleOutEvents": [],
      "macro4H": "RANGING",
      "invalidationLevel": null,
      "structureType": null,
      "status": "CLOSED",
      "exitPrice": 7418.75,
      "exitTime": 1779116487787,
      "pnl": -35,
      "paper": true,
      "mode": "PAPER",
      "exitTimeET": "11:01:27",
      "exitReason": "FUT_STOP_HIT",
      "pnlPoints": -7,
      "pnlRemainingLeg": -35,
      "holdMins": 8.5,
      "win": false
    },
    {
      "requestId": "FUT_CALLS_HL_1779115979775_e",
      "instrument": "MES1!",
      "signal": "CALLS",
      "engine": "HL",
      "confidence": "MEDIUM",
      "tier": "A",
      "contracts": 1,
      "originalContracts": 1,
      "entryPrice": 7425.75,
      "fillPrice": 7425.75,
      "fillTime": 1779115979792,
      "fillTimeET": "10:52:59",
      "entryTimeET": "10:52:59",
      "pointValue": 5,
      "stage": "STAGE_1_ARMED",
      "stopPrice": 7422.75,
      "stopPoints": 3,
      "targetPrice": 7431.75,
      "targetPoints": 6,
      "peakFavorablePrice": 7425.75,
      "trailStopPrice": null,
      "lockedStopLevel": "NONE",
      "cumulativePartialPnL": 0,
      "scaleOutEvents": [],
      "macro4H": "RANGING",
      "invalidationLevel": null,
      "structureType": null,
      "status": "CLOSED",
      "exitPrice": 7418.75,
      "exitTime": 1779116487804,
      "pnl": -35,
      "paper": true,
      "mode": "PAPER",
      "exitTimeET": "11:01:27",
      "exitReason": "FUT_STOP_HIT",
      "pnlPoints": -7,
      "pnlRemainingLeg": -35,
      "holdMins": 8.5,
      "win": false
    }
  ],
  "dailyPnL": {
    "2026-05-17": 76.25,
    "2026-05-18": -237.5
  },
  "tierStats": {
    "A": {
      "trades": 9,
      "wins": 2,
      "losses": 7,
      "pnl": -187.5
    },
    "B": {
      "trades": 11,
      "wins": 5,
      "losses": 6,
      "pnl": 26.25
    },
    "C": {
      "trades": 0,
      "wins": 0,
      "losses": 0,
      "pnl": 0
    }
  }
}